st_fa4.v
module st_fa(Co, S, A, B, Ci);

    output Co, S;

    input A, B, Ci;

    wire w1, w2, w3;


    // COLOANA 1
    xor(S, A, B, Ci);

    and(w1, A, B);

    or(w2, A, B);

    // COLOANA 2
    and(w3, Ci, w2);

    // COLOANA 3 

    or(Co, w1, w3);

endmodule 

module st_fa4(Co, S, A, B, Ci);

    output Co;
    output[3:0] S;

    input Ci;
    input[3:0] A, B;

    wire[2:0] w;


    st_fa lsb(w[0], S[0], A[0], B[0], Ci);

    st_fa bit1(w[1], S[1], A[1], B[1], w[0]);

    st_fa bit2(w[2], S[2], A[2], B[2], w[1]);

    st_fa msb(Co, S[3], A[3], B[3], w[2]);

endmodule

module st_fa4_tb();

    reg Ci;
    reg[3:0] a, b;

    wire[3:0] S;
    wire Co;

    integer i;

    initial begin


        $dumpfile("st_fa4");
        $dumpvars;


        a = 0; b = 0; Ci = 0;

        for(i = 0; i < 16; i++) begin 
            #10 a = $random;
            b = $random;
            Ci = $random;

        end 

        #10 $finish;

    end;

    st_fa4 st_fa4_1(Co, S, a, b, Ci);

endmodule

st_fa4.vcd
$date
	Thu Mar 21 11:01:45 2024
$end
$version
	Icarus Verilog
$end
$timescale
	1s
$end
$scope module st_fa4_tb $end
$var wire 4 ! S [3:0] $end
$var wire 1 " Co $end
$var reg 1 # Ci $end
$var reg 4 $ a [3:0] $end
$var reg 4 % b [3:0] $end
$var integer 32 & i [31:0] $end
$scope module st_fa4_1 $end
$var wire 4 ' A [3:0] $end
$var wire 4 ( B [3:0] $end
$var wire 1 # Ci $end
$var wire 3 ) w [2:0] $end
$var wire 4 * S [3:0] $end
$var wire 1 " Co $end
$scope module bit1 $end
$var wire 1 + A $end
$var wire 1 , B $end
$var wire 1 - Ci $end
$var wire 1 . Co $end
$var wire 1 / S $end
$var wire 1 0 w1 $end
$var wire 1 1 w2 $end
$var wire 1 2 w3 $end
$upscope $end
$scope module bit2 $end
$var wire 1 3 A $end
$var wire 1 4 B $end
$var wire 1 5 Ci $end
$var wire 1 6 Co $end
$var wire 1 7 S $end
$var wire 1 8 w1 $end
$var wire 1 9 w2 $end
$var wire 1 : w3 $end
$upscope $end
$scope module lsb $end
$var wire 1 ; A $end
$var wire 1 < B $end
$var wire 1 # Ci $end
$var wire 1 = Co $end
$var wire 1 > S $end
$var wire 1 ? w1 $end
$var wire 1 @ w2 $end
$var wire 1 A w3 $end
$upscope $end
$scope module msb $end
$var wire 1 B A $end
$var wire 1 C B $end
$var wire 1 D Ci $end
$var wire 1 " Co $end
$var wire 1 E S $end
$var wire 1 F w1 $end
$var wire 1 G w2 $end
$var wire 1 H w3 $end
$upscope $end
$upscope $end
$upscope $end
$enddefinitions $end
$comment Show the parameter values. $end
$dumpall
$end
#0
$dumpvars
0H
0G
0F
0E
0D
0C
0B
0A
0@
0?
0>
0=
0<
0;
0:
09
08
07
06
05
04
03
02
01
00
0/
0.
0-
0,
0+
b0 *
b0 )
b0 (
b0 '
b0 &
b0 %
b0 $
0#
0"
b0 !
$end
#10
1/
1-
b1 )
1=
1A
b110 !
b110 *
1@
17
19
1<
13
b1 &
1#
b1 %
b1 (
b100 $
b100 '
#20
1"
1H
1D
16
07
1:
15
b111 )
1.
b1 !
b1 *
12
0E
1G
1>
1?
0/
11
14
1C
1;
1+
03
b10 &
b1101 %
b1101 (
b11 $
b11 '
#30
0"
b1000 !
b1000 *
0H
0>
0?
1E
0G
0<
1,
04
0C
0+
13
b11 &
b10 %
b10 (
b101 $
b101 '
#40
1"
b100 !
b100 *
1H
17
18
0E
1G
14
1B
b100 &
b110 %
b110 (
b1101 $
b1101 '
#50
07
0:
05
b101 )
0.
02
b1010 !
b1010 *
1/
01
1E
1F
0,
1C
b101 &
b1100 %
b1100 (
#60
07
0:
05
0-
0.
b100 )
02
0"
0H
b1011 !
b1011 *
0=
1/
11
0F
0G
1>
0A
1<
0C
0;
1+
0B
b110 &
0#
b101 %
b101 (
b110 $
b110 '
#70
17
1:
15
1.
0/
12
1-
b111 )
b1100 !
b1100 *
1=
0>
1?
1,
1;
0+
b111 &
b111 %
b111 (
b101 $
b101 '
#80
02
0-
b110 )
1"
0=
b1 !
b1 *
1H
1>
0?
07
08
0/
10
0E
1G
0<
04
1+
1B
b1000 &
b10 %
b10 (
b1111 $
b1111 '
#90
0"
1E
0H
0D
b1101 !
b1101 *
06
17
0:
05
b0 )
0.
00
01
1<
0,
14
0;
0+
03
b1001 &
b101 %
b101 (
b1000 $
b1000 '
#100
1H
1/
1D
1-
b101 )
1"
b1011 !
b1011 *
16
1=
1E
1F
1?
07
18
1A
1C
1;
13
b1010 &
1#
b1101 %
b1101 (
b1101 $
b1101 '
#110
0"
17
0H
0/
15
0D
0-
b10 )
1.
02
06
b1101 !
b1101 *
0=
0?
10
11
08
09
1E
0F
0A
0<
1,
04
1+
03
0B
b1011 &
0#
b1010 %
b1010 (
b11 $
b11 '
#120
07
02
05
0-
b0 )
b1011 !
b1011 *
0.
0=
0@
1/
00
0A
0;
0+
b1100 &
1#
b0 $
b0 '
#130
1D
12
16
1-
1:
15
1=
b111 )
1A
1.
b1010 !
b1010 *
0>
1@
1E
0G
1/
10
07
19
1<
0C
1+
13
b1101 &
b11 %
b11 (
b110 $
b110 '
#140
0D
b11 )
0"
06
0H
b1111 !
b1111 *
0:
1E
1G
1>
1?
17
09
1C
1;
03
b1110 &
b1011 %
b1011 (
b11 $
b11 '
#150
1"
0E
1H
1D
0/
02
0-
16
b110 )
b1 !
b1 *
1:
0=
0A
07
19
0?
0@
0<
14
0;
b1111 &
b1110 %
b1110 (
b10 $
b10 '
#160
1/
12
1-
b111 )
1=
b10 !
b10 *
1?
1@
0>
1<
04
0C
1;
13
1B
b10000 &
0#
b11 %
b11 (
b1111 $
b1111 '
