subtractors/st_fs.v
module st_fs(Bo, D, A, B, Bi);

    output Bo, D;

    input A, B, Bi;

    wire w1, w2, w3;


    // COLOANA 1
    xor(D, A, B, Bi);

    xor(w1, A, B);

    and(w2, A, B);

    // COLOANA 2
    and(w3, Bi, w1);

    // COLOANA 3 

    or(Bo, w2, w3);

endmodule 

module st_fs_tb();

reg a, b, Bi;
wire Bo, D;

initial begin


$dumpfile("st_fs");
$dumpvars;

a = 0; b = 0; Bi = 0;

#5 Bi = 1;
#5 b = 1;
#5 Bi = 0;
#5 a = 1;
#5 b = 0;
#5 Bi = 1;
#5 b = 1;
#5 $finish;

end 

st_fs st_fs_1(Bo, D, a, b, Bi);


endmodule

subtractors/st_fs.vcd
$date
	Thu Mar 21 12:37:07 2024
$end
$version
	Icarus Verilog
$end
$timescale
	1s
$end
$scope module st_fs_tb $end
$var wire 1 ! D $end
$var wire 1 " Bo $end
$var reg 1 # Bi $end
$var reg 1 $ a $end
$var reg 1 % b $end
$scope module st_fs_1 $end
$var wire 1 $ A $end
$var wire 1 % B $end
$var wire 1 # Bi $end
$var wire 1 " Bo $end
$var wire 1 ! D $end
$var wire 1 & w1 $end
$var wire 1 ' w2 $end
$var wire 1 ( w3 $end
$upscope $end
$upscope $end
$enddefinitions $end
$comment Show the parameter values. $end
$dumpall
$end
#0
$dumpvars
0(
0'
0&
0%
0$
0#
0"
0!
$end
#5
1!
1#
#10
1"
1(
0!
1&
1%
#15
0"
1!
0(
0#
#20
1"
0!
0&
1'
1$
#25
0"
1!
1&
0'
0%
#30
1"
0!
1(
1#
#35
0(
1!
0&
1'
1%
